imghst/__init__.py
imghst/__version__.py
imghst/entry.py
imghst/__pycache__/__init__.cpython-37.pyc
imghst/__pycache__/__version__.cpython-37.pyc
imghst/__pycache__/entry.cpython-37.pyc
imghst/app/app.py
imghst/app/request_models.py
imghst/app/__pycache__/app.cpython-37.pyc
imghst/app/__pycache__/entry.cpython-37.pyc
imghst/app/__pycache__/request_models.cpython-37.pyc
imghst/app/configuration/__init__.py
imghst/app/configuration/configuration.py
imghst/app/configuration/__pycache__/__init__.cpython-37.pyc
imghst/app/configuration/__pycache__/configuration.cpython-37.pyc
imghst/app/configuration/unique_generators/__init__.py
imghst/app/configuration/unique_generators/uuid_based.py
imghst/app/configuration/unique_generators/__pycache__/__init__.cpython-37.pyc
imghst/app/configuration/unique_generators/__pycache__/uuid_based.cpython-37.pyc
imghst-0.5.2.dist-info/METADATA
imghst-0.5.2.dist-info/WHEEL
imghst-0.5.2.dist-info/entry_points.txt
imghst-0.5.2.dist-info/top_level.txt
imghst-0.5.2.dist-info/RECORD
