Metadata-Version: 2.1
Name: imghst
Version: 0.5.2
Summary: A simple and fast image hoster for applications like ShareX.
Home-page: https://github.com/ms7m/imghst
Author: Mustafa Mohamed
Author-email: git@ms7m.me
License: UNKNOWN
Platform: UNKNOWN
Classifier: Programming Language :: Python :: 3
Classifier: License :: OSI Approved :: MIT License
Classifier: Operating System :: OS Independent
Requires-Python: >=3.6.0
Requires-Dist: aiofiles (==0.6.0)
Requires-Dist: click (==7.1.2)
Requires-Dist: fastapi (==0.61.1)
Requires-Dist: filetype (==1.0.7)
Requires-Dist: h11 (==0.11.0)
Requires-Dist: loguru (==0.5.3)
Requires-Dist: pydantic (==1.7.1)
Requires-Dist: python-multipart (==0.0.5)
Requires-Dist: six (==1.15.0)
Requires-Dist: starlette (==0.13.6)
Requires-Dist: typer (==0.3.2)
Requires-Dist: typing-extensions (==3.7.4.3)
Requires-Dist: uvicorn (==0.12.2)
Requires-Dist: colorama (==0.4.4)
